{
  "version": 1,
  "serviceConfiguration": {
    "apiName": "skl",
    "serviceName": "AppSync",
    "gqlSchemaPath": "/tmp/amplify-66e5f426-9e23-44fb-91ba-827dfb81c7db/amplify/backend/api/skl/schema.graphql",
    "defaultAuthType": {
      "mode": "API_KEY",
      "keyDescription": "api key description",
      "expirationTime": 30
    },
    "additionalAuthTypes": [
      {
        "mode": "AWS_IAM"
      }
    ],
    "conflictResolution": {
      "defaultResolutionStrategy": {
        "type": "AUTOMERGE"
      }
    }
  }
}